setup.py
protime/__init__.py
protime/protime.py
protime/time.py
protime.egg-info/PKG-INFO
protime.egg-info/SOURCES.txt
protime.egg-info/dependency_links.txt
protime.egg-info/not-zip-safe
protime.egg-info/top_level.txt