Metadata-Version: 2.1
Name: protime
Version: 0.1
Summary: Shortens Writing Waiting Time Using Symbols (1s, 1m, 1h, 1d, 1w)
Home-page: UNKNOWN
Author: Abdulrahman Abouldahab
License: UNKNOWN
Platform: UNKNOWN
